waktusolat/__init__.py
waktusolat/client.py
waktusolat/exceptions.py
waktusolat-1.0.0.dist-info/LICENSE
waktusolat-1.0.0.dist-info/WHEEL
waktusolat-1.0.0.dist-info/METADATA
waktusolat-1.0.0.dist-info/RECORD
